stringpod/__init__.py
stringpod/cli.py
stringpod/language.py
stringpod/normalizer.py
stringpod/number.py
stringpod/pinyin.py
stringpod/segmentation.py
stringpod/stringpod.py
stringpod/utils.py
stringpod-0.2.2.dist-info/LICENSE
stringpod-0.2.2.dist-info/METADATA
stringpod-0.2.2.dist-info/WHEEL
stringpod-0.2.2.dist-info/entry_points.txt
stringpod-0.2.2.dist-info/RECORD
