Metadata-Version: 2.3
Name: stringpod
Version: 0.2.2
Summary: Matching texts across languages.
License: MIT
Author: Jasmine Yeung
Author-email: yeungjyy@gmail.com
Requires-Python: >=3.12.3,<4.0
Classifier: Development Status :: 2 - Pre-Alpha
Classifier: Intended Audience :: Developers
Classifier: License :: OSI Approved :: MIT License
Classifier: Natural Language :: English
Classifier: Programming Language :: Python :: 3
Classifier: Programming Language :: Python :: 3.13
Classifier: Programming Language :: Python :: 3.12
Provides-Extra: dev
Provides-Extra: docs
Provides-Extra: test
Requires-Dist: black (>=25.1.0,<26.0.0) ; extra == "test"
Requires-Dist: bump2version (>=1.0.1,<2.0.0) ; extra == "dev"
Requires-Dist: flake8 (>=7.1.2,<8.0.0) ; extra == "test"
Requires-Dist: flake8-docstrings (>=1.6.0,<2.0.0) ; extra == "test"
Requires-Dist: hanzidentifier (>=1.3.0,<2.0.0)
Requires-Dist: isort (>=6.0.0,<7.0.0) ; extra == "test"
Requires-Dist: jieba (>=0.42.1,<0.43.0)
Requires-Dist: langdetect (>=1.0.9,<2.0.0)
Requires-Dist: mkdocs (>=1.6.1,<2.0.0) ; extra == "docs"
Requires-Dist: mkdocs-autorefs (>=1.3.1,<2.0.0) ; extra == "docs"
Requires-Dist: mkdocs-include-markdown-plugin (>=1.0.0,<2.0.0) ; extra == "docs"
Requires-Dist: mkdocs-material (>=9.6.5,<10.0.0) ; extra == "docs"
Requires-Dist: mkdocstrings (>=0.28.1,<0.29.0) ; extra == "docs"
Requires-Dist: mkdocstrings-python (>=1.16.1,<2.0.0) ; extra == "docs"
Requires-Dist: mypy (>=1.15.0,<2.0.0) ; extra == "test"
Requires-Dist: number-parser (>=0.3.2,<0.4.0)
Requires-Dist: opencc (>=1.1.9,<2.0.0)
Requires-Dist: pip (>=25.0.1,<26.0.0) ; extra == "dev"
Requires-Dist: pre-commit (>=4.1.0,<5.0.0) ; extra == "dev"
Requires-Dist: pypinyin (>=0.53.0,<0.54.0)
Requires-Dist: pytest (>=8.3.4,<9.0.0) ; extra == "test"
Requires-Dist: pytest-cov (>=6.0.0,<7.0.0) ; extra == "test"
Requires-Dist: python-semantic-release (>=9.20.0,<10.0.0) ; extra == "dev"
Requires-Dist: toml (>=0.10.2,<0.11.0) ; extra == "dev"
Requires-Dist: tox (>=4.24.1,<5.0.0) ; extra == "dev"
Requires-Dist: twine (>=6.1.0,<7.0.0) ; extra == "dev"
Requires-Dist: virtualenv (>=20.29.2,<21.0.0) ; extra == "dev"
Project-URL: Homepage, https://github.com/jyyyeung/stringpod
